khldaemon/__init__.py
khldaemon/__main__.py
khldaemon/config.py
khldaemon/khld_server.py
khldaemon/api/__init__.py
khldaemon/api/all/__init__.py
khldaemon/api/command/__init__.py
khldaemon/api/decorator/__init__.py
khldaemon/api/interface/__init__.py
khldaemon/api/types/__init__.py
khldaemon/api/utils/__init__.py
khldaemon/cli/__init__.py
khldaemon/cli/cli_entry.py
khldaemon/command/__init__.py
khldaemon/command/command_manager.py
khldaemon/command/command_source.py
khldaemon/command/builder/__init__.py
khldaemon/command/builder/command_builder_util.py
khldaemon/command/builder/exception.py
khldaemon/command/builder/nodes/__init__.py
khldaemon/command/builder/nodes/arguments.py
khldaemon/command/builder/nodes/basic.py
khldaemon/constants/__init__.py
khldaemon/constants/core_constant.py
khldaemon/plugin/__init__.py
khldaemon/plugin/interface.py
khldaemon/plugin/plugin_manager.py
khldaemon/plugin/builtin/__init__.py
khldaemon/plugin/builtin/khl_plugin.py
khldaemon/plugin/type/__init__.py
khldaemon/plugin/type/meta.py
khldaemon/plugin/type/plugin.py
khldaemon/resources/default_config.yml
khldaemon/utils/__init__.py
khldaemon/utils/logger.py
khldaemon/utils/serializer.py
khldaemon-0.1.2.dist-info/LICENSE
khldaemon-0.1.2.dist-info/METADATA
khldaemon-0.1.2.dist-info/WHEEL
khldaemon-0.1.2.dist-info/top_level.txt
khldaemon-0.1.2.dist-info/RECORD
