Metadata-Version: 2.1
Name: khldaemon
Version: 0.1.2
Summary: Plugin system based on khl.py
Home-page: https://github.com/DancingSnow0517/KHLDaemon
Author: DancingSnow
License: UNKNOWN
Platform: UNKNOWN
Classifier: License :: OSI Approved :: GNU Lesser General Public License v3 (LGPLv3)
Classifier: Programming Language :: Python
License-File: LICENSE
Requires-Dist: khl.py (>=0.2.9)
Requires-Dist: ruamel.yaml (~=0.17.16)
Requires-Dist: parse (>=1.18.0)
Requires-Dist: colorlog (>=6.6.0)
Requires-Dist: colorama (>=0.4.4)
Requires-Dist: nest-asyncio (>=1.5.5)
